tests/__init__.py
tests/env.py
tests/test.py
wudder/__init__.py
wudder/client.py
wudder/event.py
wudder/exceptions.py
wudder/graphn.py
wudder/utils.py
wudder/wudder.py
wudder-3.2110.0.dist-info/LICENSE
wudder-3.2110.0.dist-info/METADATA
wudder-3.2110.0.dist-info/WHEEL
wudder-3.2110.0.dist-info/top_level.txt
wudder-3.2110.0.dist-info/RECORD
