Metadata-Version: 2.1
Name: wudder
Version: 3.2110.0
Summary: Create blockchain certificates for all the events of your business processes. In Ethereum. At scale.
Home-page: https://github.com/wuddertech/python-sdk
Author: Rodrigo Martínez Castaño
Author-email: rodrigo@martinez.gal
License: GNU General Public License v3 (GPLv3)
Platform: UNKNOWN
Classifier: Development Status :: 4 - Beta
Classifier: Environment :: Console
Classifier: Intended Audience :: Developers
Classifier: License :: OSI Approved :: GNU General Public License v3 (GPLv3)
Classifier: Operating System :: POSIX :: Linux
Classifier: Programming Language :: Python :: 3.6
Classifier: Programming Language :: Python :: Implementation :: PyPy
Classifier: Topic :: Software Development :: Libraries :: Python Modules
License-File: LICENSE
Requires-Dist: requests
Requires-Dist: easygraphql
Requires-Dist: easyweb3
Requires-Dist: digsig (<2.0.0,>=1.216.0)
